faker_blog/__init__.py
faker_blog/provider.py
faker_blog/utils.py
faker_blog/templates/__init__.py
faker_blog/templates/html.py
faker_blog/templates/text.py
faker_blog_provider-0.0.3.dist-info/LICENSE
faker_blog_provider-0.0.3.dist-info/METADATA
faker_blog_provider-0.0.3.dist-info/WHEEL
faker_blog_provider-0.0.3.dist-info/top_level.txt
faker_blog_provider-0.0.3.dist-info/RECORD
