Metadata-Version: 2.1
Name: faker_blog_provider
Version: 0.0.3
Summary: A Faker provider that generates fake blog content in Brazilian Portuguese as blog titles, blog posts, images, tags, and more.
Author-email: Adaías Magdiel <eu@adaiasmagdiel.com>
License: Copyright (c) 2023 Adaías Magdiel
Project-URL: Homepage, https://github.com/AdaiasMagdiel/python-faker-blog
Project-URL: Issues, https://github.com/AdaiasMagdiel/python-faker-blog/issues
Keywords: faker,provider,blog content,fake blog data,fake article content
Classifier: Programming Language :: Python :: 3
Classifier: Programming Language :: Python :: 3.8
Classifier: Programming Language :: Python :: 3.9
Classifier: Programming Language :: Python :: 3.10
Classifier: Programming Language :: Python :: 3.11
Classifier: License :: OSI Approved :: MIT License
Classifier: Operating System :: OS Independent
Classifier: Intended Audience :: Developers
Classifier: Intended Audience :: Information Technology
Classifier: Natural Language :: Portuguese (Brazilian)
Classifier: Topic :: Utilities
Requires-Python: >=3.8
License-File: LICENSE
Requires-Dist: Faker ==20.0.3
